{"WEAPON LAWS": "weapon laws", "WARRANTS": "warrants", "NON-CRIMINAL": "non-criminal", "ASSAULT": "personal crimes", "OTHER OFFENSES": "other", "MISSING PERSON": "personal crimes", "LARCENY/THEFT": "property crimes", "BURGLARY": "property crimes", "STOLEN PROPERTY": "property crimes", "ROBBERY": "property crimes", "FRAUD": "financial ", "DRUG/NARCOTIC": "statutory crimes", "VEHICLE THEFT": "property crimes", "RECOVERED VEHICLE": "property crimes", "VANDALISM": "property crimes", "ARSON": "personal crimes", "PROSTITUTION": "statutory crimes", "SECONDARY CODES": "secondary codes", "SUSPICIOUS OCC": "suspicious occ", "DRUNKENNESS": "statutory crimes", "TRESPASS": "trespass", "SEX OFFENSES, NON FORCIBLE": "statutory crimes", "SEX OFFENSES, FORCIBLE": "statutory crimes", "RUNAWAY": "runaway", "KIDNAPPING": "personal crimes", "DISORDERLY CONDUCT": "statutory crimes", "DRIVING UNDER THE INFLUENCE": "statutory crimes", "FORGERY/COUNTERFEITING": "financial ", "EMBEZZLEMENT": "financial ", "BRIBERY": "financial ", "FAMILY OFFENSES": "family offenses", "GAMBLING": "financial ", "SUICIDE": "suicide", "LIQUOR LAWS": "liquor laws", "EXTORTION": "property crimes", "LOITERING": "statutory crimes", "TREA": "trespass", "BAD CHECKS": "financial ", "PORNOGRAPHY/OBSCENE MAT": "statutory crimes"}